LICENSE
pipf/__init__.py
pipf/app.py
pipf/fzf/__init__.py
pipf/fzf/__main__.py
pipf/fzf/packages_list/__main__.py
pipf/fzf/preview/__main__.py
pipf/fzf/run.sh
pipf-0.1.2.dist-info/entry_points.txt
pipf-0.1.2.dist-info/LICENSE
pipf-0.1.2.dist-info/WHEEL
pipf-0.1.2.dist-info/METADATA
pipf-0.1.2.dist-info/RECORD
